empress-sdk/__init__.py
empress-sdk/api_client.py
empress-sdk/api_response.py
empress-sdk/configuration.py
empress-sdk/exceptions.py
empress-sdk/py.typed
empress-sdk/rest.py
empress-sdk/api/__init__.py
empress-sdk/api/default_api.py
empress-sdk/models/__init__.py
empress-sdk/models/empress_post200_response.py
empress-sdk/models/empress_post_request.py
test/__init__.py
test/test_default_api.py
test/test_empress_post200_response.py
test/test_empress_post_request.py
empress_eco_python-1.0.6.dist-info/METADATA
empress_eco_python-1.0.6.dist-info/WHEEL
empress_eco_python-1.0.6.dist-info/top_level.txt
empress_eco_python-1.0.6.dist-info/RECORD
